{
  "id": 9042806,
  "title": "Festive moments with friends",
  "description": "Eat, Drink, and be Merry! Winter is all about staying indoors and getting cosy. Filled with photos of friends gathered by the fire and families sharing festive treats - explore our latest collection celebrating time spent together. ",
  "published_at": "2019-12-14T04:05:22-05:00",
  "updated_at": "2019-12-17T06:43:14-05:00",
  "curated": false,
  "featured": true,
  "total_photos": 45,
  "private": false,
  "share_key": "c16cfd5ce851c11ef4ff884047e1d8e6"

}